wordify/__init__.py
wordify/converter.py
wordify-1.5.0.dist-info/LICENSE
wordify-1.5.0.dist-info/METADATA
wordify-1.5.0.dist-info/WHEEL
wordify-1.5.0.dist-info/top_level.txt
wordify-1.5.0.dist-info/RECORD
