Metadata-Version: 2.1
Name: wordify
Version: 1.5.0
Summary: A Python module to convert numerical values into their word representation.
Home-page: https://github.com/fathiabdelmalek/wordify.git
Author: Fathi Abdelmalek
Author-email: abdelmalek.fathi.2001@gmail.com
Classifier: Programming Language :: Python :: 3
Classifier: License :: OSI Approved :: MIT License
Classifier: Operating System :: OS Independent
License-File: LICENSE
